Workbook

Sheet Raw Sales
A1: Date | B1: Sale ID | C1: Salesperson | D1: Product | E1: Quantity | F1: Unit Price | G1: Payment Method | H1: Total Sales
A2: 46296 | B2: S001 | C2: Ananya | D2: Notebook | E2: 10 | F2: 40 | G2: Cash | H2: =E2*F2
A3: 46296 | B3: S002 | C3: Rahul | D3: Pen | E3: 20 | F3: 10 | G3: UPI | H3: =E3*F3
A4: 46297 | B4: S003 | C4: Meera | D4: Backpack | E4: 2 | F4: 650 | G4: Card | H4: =E4*F4
A5: 46298 | B5: S004 | C5: Arjun | D5: Notebook | E5: 15 | F5: 40 | G5: UPI | H5: =E5*F5
A6: 46302 | B6: S005 | C6: Ananya | D6: Water Bottle | E6: 5 | F6: 180 | G6: Cash | H6: =E6*F6
A7: 46303 | B7: S006 | C7: Rahul | D7: Pen | E7: 30 | F7: 10 | G7: UPI | H7: =E7*F7
A8: 46307 | B8: S007 | C8: Meera | D8: Backpack | E8: 1 | F8: 650 | G8: Card | H8: =E8*F8
A9: 46310 | B9: S008 | C9: Arjun | D9: Notebook | E9: 8 | F9: 40 | G9: Cash | H9: =E9*F9
A10: 46315 | B10: S009 | C10: Ananya | D10: Water Bottle | E10: 3 | F10: 180 | G10: UPI | H10: =E10*F10
A11: 46321 | B11: S010 | C11: Rahul | D11: Pen | E11: 12 | F11: 10 | G11: Cash | H11: =E11*F11

Sheet Summary
A1: SALES TRACKER SUMMARY
A3: Daily totals | E3: Manual verification
A4: Date | B4: Total Sales | E4: Total rows | F4: =COUNTA('Raw Sales'!B2:B1000)
A5: 46296 | B5: =SUMIFS('Raw Sales'!$H$2:$H$1000,'Raw Sales'!$A$2:$A$1000,A5,'Raw Sales'!$A$2:$A$1000,"<"&A5+1) | E5: Grand total | F5: =SUM('Raw Sales'!H2:H1000)
A6: 46297 | B6: =SUMIFS('Raw Sales'!$H$2:$H$1000,'Raw Sales'!$A$2:$A$1000,A6,'Raw Sales'!$A$2:$A$1000,"<"&A6+1) | E6: Manual total (sample) | F6: 5330
A7: 46298 | B7: =SUMIFS('Raw Sales'!$H$2:$H$1000,'Raw Sales'!$A$2:$A$1000,A7,'Raw Sales'!$A$2:$A$1000,"<"&A7+1) | E7: Check | F7: =IF(F5=F6,"MATCH","CHECK")
A8: 46302 | B8: =SUMIFS('Raw Sales'!$H$2:$H$1000,'Raw Sales'!$A$2:$A$1000,A8,'Raw Sales'!$A$2:$A$1000,"<"&A8+1)
A9: 46303 | B9: =SUMIFS('Raw Sales'!$H$2:$H$1000,'Raw Sales'!$A$2:$A$1000,A9,'Raw Sales'!$A$2:$A$1000,"<"&A9+1)
A10: 46307 | B10: =SUMIFS('Raw Sales'!$H$2:$H$1000,'Raw Sales'!$A$2:$A$1000,A10,'Raw Sales'!$A$2:$A$1000,"<"&A10+1)
A11: 46310 | B11: =SUMIFS('Raw Sales'!$H$2:$H$1000,'Raw Sales'!$A$2:$A$1000,A11,'Raw Sales'!$A$2:$A$1000,"<"&A11+1)
A12: 46315 | B12: =SUMIFS('Raw Sales'!$H$2:$H$1000,'Raw Sales'!$A$2:$A$1000,A12,'Raw Sales'!$A$2:$A$1000,"<"&A12+1)
A13: 46321 | B13: =SUMIFS('Raw Sales'!$H$2:$H$1000,'Raw Sales'!$A$2:$A$1000,A13,'Raw Sales'!$A$2:$A$1000,"<"&A13+1)
A16: Weekly totals
A17: Week starting | B17: Week ending | C17: Total Sales
A18: 46293 | B18: 46299 | C18: =SUMIFS('Raw Sales'!$H$2:$H$1000,'Raw Sales'!$A$2:$A$1000,">="&A18,'Raw Sales'!$A$2:$A$1000,"<="&B18)
A19: 46300 | B19: 46306 | C19: =SUMIFS('Raw Sales'!$H$2:$H$1000,'Raw Sales'!$A$2:$A$1000,">="&A19,'Raw Sales'!$A$2:$A$1000,"<="&B19)
A20: 46307 | B20: 46313 | C20: =SUMIFS('Raw Sales'!$H$2:$H$1000,'Raw Sales'!$A$2:$A$1000,">="&A20,'Raw Sales'!$A$2:$A$1000,"<="&B20)
A21: 46314 | B21: 46320 | C21: =SUMIFS('Raw Sales'!$H$2:$H$1000,'Raw Sales'!$A$2:$A$1000,">="&A21,'Raw Sales'!$A$2:$A$1000,"<="&B21)
A22: 46321 | B22: 46327 | C22: =SUMIFS('Raw Sales'!$H$2:$H$1000,'Raw Sales'!$A$2:$A$1000,">="&A22,'Raw Sales'!$A$2:$A$1000,"<="&B22)
A25: Monthly totals
A26: Month | B26: Total Sales
A27: 46296 | B27: =SUMIFS('Raw Sales'!$H$2:$H$1000,'Raw Sales'!$A$2:$A$1000,">="&A27,'Raw Sales'!$A$2:$A$1000,"<"&EDATE(A27,1))
